setup.cfg
setup.py
hashicon/__init__.py
hashicon/hashicon.py
hashicon.egg-info/PKG-INFO
hashicon.egg-info/SOURCES.txt
hashicon.egg-info/dependency_links.txt
hashicon.egg-info/entry_points.txt
hashicon.egg-info/requires.txt
hashicon.egg-info/top_level.txt