Metadata-Version: 1.1
Name: hashicon
Version: 0.1.1
Summary: Create minimalistic icons from a string
Home-page: https://github.com/cabreraalex/hashicon
Author: Alex Cabrera
Author-email: alex.cabrera@gmail.com
License: MIT
Download-URL: https://github.com/cabreraalex/hashicon/tarball/0.1
Keywords: icon,PIL,hash,picture,Pillow
Platform: UNKNOWN
